odoo/addons/stock_inventory_valuation_pivot/README.rst
odoo/addons/stock_inventory_valuation_pivot/__init__.py
odoo/addons/stock_inventory_valuation_pivot/__manifest__.py
odoo/addons/stock_inventory_valuation_pivot/i18n/es.po
odoo/addons/stock_inventory_valuation_pivot/i18n/stock_inventory_valuation_pivot.pot
odoo/addons/stock_inventory_valuation_pivot/readme/CONTRIBUTORS.rst
odoo/addons/stock_inventory_valuation_pivot/readme/DESCRIPTION.rst
odoo/addons/stock_inventory_valuation_pivot/readme/USAGE.rst
odoo/addons/stock_inventory_valuation_pivot/static/description/icon.png
odoo/addons/stock_inventory_valuation_pivot/static/description/index.html
odoo/addons/stock_inventory_valuation_pivot/views/stock_account_views.xml
odoo13_addon_stock_inventory_valuation_pivot-13.0.1.1.0.dist-info/METADATA
odoo13_addon_stock_inventory_valuation_pivot-13.0.1.1.0.dist-info/WHEEL
odoo13_addon_stock_inventory_valuation_pivot-13.0.1.1.0.dist-info/top_level.txt
odoo13_addon_stock_inventory_valuation_pivot-13.0.1.1.0.dist-info/RECORD
